gprstudio/__init__.py
gprstudio/base.py
gprstudio/config.py
gprstudio/datasets.py
gprstudio/projects.py
gprstudio-0.2.8.dist-info/METADATA
gprstudio-0.2.8.dist-info/WHEEL
gprstudio-0.2.8.dist-info/RECORD
